Clict/Typedef.py
Clict/__init__.py
Clict/main.py
Clict/Clict_from/__init__.py
Clict/Clict_from/config.py
Clict/Clict_to/__init__.py
Clict/Clict_to/config.py
Clict/lib/__init__.py
Clict/lib/fnText.py
Clict/lib/fnterm.py
Clict-0.5.4.dist-info/LICENSE
Clict-0.5.4.dist-info/METADATA
Clict-0.5.4.dist-info/WHEEL
Clict-0.5.4.dist-info/top_level.txt
Clict-0.5.4.dist-info/RECORD
